core/__init__.py
core/form_generator.py
core/launcher.py
core/metadata_generator.py
core/module_generator.py
onec_contract_generator-2.2.0.dist-info/licenses/LICENSE
parsers/__init__.py
utils/__init__.py
onec_contract_generator-2.2.0.dist-info/METADATA
onec_contract_generator-2.2.0.dist-info/WHEEL
onec_contract_generator-2.2.0.dist-info/entry_points.txt
onec_contract_generator-2.2.0.dist-info/top_level.txt
onec_contract_generator-2.2.0.dist-info/RECORD
