Metadata-Version: 2.4
Name: onec-contract-generator
Version: 2.2.0
Summary: Autonomous system for generating structured JSON contracts from 1C:Enterprise configurations
Home-page: https://github.com/onec-contract-generator/onec-contract-generator
Author: 1C Contract Generator Team
Author-email: 1C Contract Generator Team <support@onec-contract-generator.dev>
Maintainer-email: 1C Contract Generator Team <support@onec-contract-generator.dev>
License-Expression: MIT
Project-URL: Homepage, https://github.com/onec-contract-generator/onec-contract-generator
Project-URL: Documentation, https://github.com/onec-contract-generator/onec-contract-generator#readme
Project-URL: Repository, https://github.com/onec-contract-generator/onec-contract-generator
Project-URL: Bug Tracker, https://github.com/onec-contract-generator/onec-contract-generator/issues
Project-URL: Changelog, https://github.com/onec-contract-generator/onec-contract-generator/blob/main/CHANGELOG.md
Keywords: 1c,enterprise,metadata,contracts,generation,analysis,json,xml,documentation
Classifier: Development Status :: 4 - Beta
Classifier: Intended Audience :: Developers
Classifier: Operating System :: OS Independent
Classifier: Programming Language :: Python :: 3
Classifier: Programming Language :: Python :: 3.7
Classifier: Programming Language :: Python :: 3.8
Classifier: Programming Language :: Python :: 3.9
Classifier: Programming Language :: Python :: 3.10
Classifier: Programming Language :: Python :: 3.11
Classifier: Programming Language :: Python :: 3.12
Classifier: Topic :: Software Development :: Libraries :: Python Modules
Classifier: Topic :: Software Development :: Code Generators
Classifier: Topic :: Office/Business :: Financial :: Accounting
Classifier: Topic :: Text Processing :: Markup :: XML
Classifier: Topic :: Software Development :: Documentation
Requires-Python: >=3.7
License-File: LICENSE
Provides-Extra: dev
Requires-Dist: pytest>=6.0.0; extra == "dev"
Requires-Dist: pytest-cov>=2.10.0; extra == "dev"
Requires-Dist: black>=21.0.0; extra == "dev"
Requires-Dist: flake8>=3.8.0; extra == "dev"
Requires-Dist: mypy>=0.800; extra == "dev"
Provides-Extra: docs
Requires-Dist: sphinx>=4.0.0; extra == "docs"
Requires-Dist: sphinx-rtd-theme>=1.0.0; extra == "docs"
Dynamic: author
Dynamic: home-page
Dynamic: license-file
Dynamic: requires-python
